{
    "caja_id": 1,
    "business_name": "MI NEGOCIO",
    "currency_symbol": "$",
    "currency_code": "ARS",
    "address": "Calle y Numero",
    "phone": "11-0000-0000",
    "footer_message": "Gracias por su compra!",
    "tax_percentage": 0.0,
    "theme": "midnight",
    "balanza_habilitada": false,
    "balanza_prefijo": "20",
    "balanza_modo": "Peso Neto (Kg)",
    "balanza_plu_inicio": 3,
    "balanza_plu_largo": 5,
    "balanza_val_inicio": 8,
    "balanza_val_largo": 5,
    "balanza_divisor": 1000,
    "business_cuit": "CUIT: 00-00000000-0",
    "business_iibb": "",
    "business_inicio_actividades": "",
    "printer_name": "",
    "mp_access_token": "",
    "ticket_printer": "",
    "drawer_open_cash": true,
    "drawer_open_card": false,
    "drawer_open_transfer": false,
    "drawer_open_mixed": true,
    "ticket_printer_2": "",
    "drawer_sensor_inverted": false,
    "printer_3nstar_mode": false,
    "opos_drawer_name": "caja",
    "drawer_kick_pin": 0,
    "db_path": "",
    "db_name": "punpro.db",
    "server_password": "1234",
    "update_server_ip": "",
    "update_auth_token": "1234",
    "local_pin": "1234",
    "shared_folder_name": "cajafacil pro",
    "fiscal_printer_mode": false,
    "fiscal_printer_model": "",
    "factura_electronica_mode": false,
    "cert_key_path": "certificados/clave.key",
    "cert_crt_path": "certificados/certificado.crt",
    "arca_sandbox_mode": true,
    "arca_punto_venta": 1,
    "github_update_repo": "cesarmaciel1234/cajafacil-pro",
    "github_update_enabled": true
}
